md2stl/__init__.py
md2stl/build_structure.py
md2stl/extract_molecules.py
md2stl/make_objects.py
md2stl/system_class.py
md2stl-0.1.dist-info/LICENSE
md2stl-0.1.dist-info/METADATA
md2stl-0.1.dist-info/WHEEL
md2stl-0.1.dist-info/top_level.txt
md2stl-0.1.dist-info/RECORD
