Metadata-Version: 2.1
Name: md2stl
Version: 0.1
Summary: Python tools to convert a MD simulation file into a .stl file ready to be 3d printed.
Home-page: https://github.com/vivien-walter/md2stl
Author: Vivien WALTER
Author-email: walter.vivien@gmail.com
License: GPL3.0
Download-URL: https://github.com/vivien-walter/md2stl/archive/v0.1.tar.gz
Platform: UNKNOWN
Requires-Dist: numpy
Requires-Dist: numpy-stl
Requires-Dist: MDAnalysis
Requires-Dist: tqdm
